alsi/VERSION
alsi/__init__.py
alsi/exceptions.py
alsi/mappings.py
alsi/pandas_client.py
alsi/raw_client.py
alsi/timefilter.py
tests/__init__.py
tests/test_pandas_client.py
tests/test_raw_client.py
alsi_py-1.1.1.dist-info/LICENSE
alsi_py-1.1.1.dist-info/METADATA
alsi_py-1.1.1.dist-info/WHEEL
alsi_py-1.1.1.dist-info/top_level.txt
alsi_py-1.1.1.dist-info/RECORD
