Metadata-Version: 2.1
Name: alsi-py
Version: 1.1.1
Summary: A library to query ALSI data
Author: Roiti LTD
Author-email: opensource@roiti.com
Maintainer-email: gkuka@roiti.com, ntoshev@roiti.com, shalvadzhiev@roiti.com, tkirilov@roiti.com
License: MIT License
Classifier: Programming Language :: Python :: 3
Classifier: Operating System :: OS Independent
Requires-Python: >=3.7
License-File: LICENSE
Requires-Dist: aiohttp (<4.0.0,>=3.8.0)
Requires-Dist: pandas (<2,>=1.0)
Requires-Dist: typing-extensions (<5,>=4.2.0)
